flask_taxonomies/__init__.py
flask_taxonomies/api.py
flask_taxonomies/bulk.py
flask_taxonomies/config.py
flask_taxonomies/constants.py
flask_taxonomies/ext.py
flask_taxonomies/fields.py
flask_taxonomies/marshmallow.py
flask_taxonomies/models.py
flask_taxonomies/proxies.py
flask_taxonomies/query.py
flask_taxonomies/routing.py
flask_taxonomies/signals.py
flask_taxonomies/term_identification.py
flask_taxonomies/utils.py
flask_taxonomies/alembic/env.py
flask_taxonomies/views/__init__.py
flask_taxonomies/views/common.py
flask_taxonomies/views/paginator.py
flask_taxonomies/views/perms.py
flask_taxonomies/views/taxonomy.py
flask_taxonomies/views/taxonomy_term.py
flask_taxonomies-7.0.3.dist-info/LICENSE
flask_taxonomies-7.0.3.dist-info/METADATA
flask_taxonomies-7.0.3.dist-info/WHEEL
flask_taxonomies-7.0.3.dist-info/top_level.txt
flask_taxonomies-7.0.3.dist-info/RECORD
