Metadata-Version: 2.1
Name: flask-taxonomies
Version: 7.0.3
Summary: UNKNOWN
Home-page: UNKNOWN
License: Creative Commons Attribution-Noncommercial-Share Alike license
Platform: UNKNOWN
Requires-Dist: flask
Requires-Dist: flask-sqlalchemy
Requires-Dist: blinker
Requires-Dist: sqlalchemy-utils
Requires-Dist: python-slugify
Requires-Dist: jsonpatch
Requires-Dist: webargs (<6.0.0)
Requires-Dist: jsonpointer
Requires-Dist: LinkHeader
Requires-Dist: flask-principal
Requires-Dist: luqum
Provides-Extra: migrate
Requires-Dist: flask-migrate ; extra == 'migrate'
Provides-Extra: postgresql
Requires-Dist: psycopg2 ; extra == 'postgresql'
Provides-Extra: sqlite
Provides-Extra: tests
Requires-Dist: pytest (>=5.4) ; extra == 'tests'
Requires-Dist: pytest-flask-sqlalchemy ; extra == 'tests'
Requires-Dist: md-toc ; extra == 'tests'
Requires-Dist: isort ; extra == 'tests'
Requires-Dist: check-manifest ; extra == 'tests'
Requires-Dist: pytest-coverage ; extra == 'tests'
Requires-Dist: pytest-pep8 ; extra == 'tests'
